{
  "case_id": "afa1f607",
  "clinical_variables": {
    "primary_condition": "Acute symptomatic seizures due to recent traumatic brain injury",
    "comorbidities": [
      "Migraine",
      "Depression"
    ],
    "age": 35,
    "sex": "M",
    "risk_factors": [
      "Family history of epilepsy",
      "Head trauma",
      "Alcohol use during pregnancy"
    ]
  },
  "difficulty": "medium",
  "case_type": "acute",
  "intended_outcome": "improving",
  "narrative": "John Martinez, a 35\u2011year\u2011old construction supervisor, had never had a medical problem serious enough to make him think twice about his health. He could walk a mile without a breath of air, drank a few beers on the weekend, and had a longstanding history of episodic migraines that he typically managed with over\u2011the\u2011counter analgesics. He also had been hospitalized a few times for major depressive episodes, for which he had been on a stable dose of sertraline. His father had a history of untreated seizures in his thirties, and his mother, who had been a chronic drinker during her pregnancy, had passed down a family pedigree of neurological susceptibility that John had acknowledged only in passing.\n\nOn a rainy Thursday afternoon, the day that would become the turning point of his medical story, John was attempting to lift a heavy metal beam when the load tipped. He slipped on the slick floor, slammed his forehead against a steel beam, and fell heavily onto the concrete. He heard the thud and, momentarily, the world swerved in a green haze of motion. The next thing he remembered was the white light of the emergency department, the smell of antiseptic, and the sight of a nurse holding his wrist and pulling a cuff around his arm.\n\n**Day 0\u20131: ED and First Seizure**\n\nAt the ED, a cranial CT scan revealed a left frontal subdural hematoma measuring 2\u202fmm in thickness with a small midline shift. There were no signs of skull fracture. John was admitted to the neurosurgical unit for close observation. He slept poorly that evening, waking every hour with a throbbing headache that had a migraine quality\u2014pulsatile, accompanied by photophobia and an aura of blurred vision. Early on the next morning, he suddenly became rigid, his left arm jerking in a stereotyped clonic motion that lasted about 18\u202fseconds before he fell to the floor. The episode was witnessed by the nurse and stopped spontaneously within a minute.\n\nLorazepam 1\u202fmg IV was given, and the patient's vital signs stabilized. The neurologist, Dr. Patel, noted the resemblance of the seizure to previous focal events seen in patients with parenchymal contusion. An electroencephalogram (EEG) was scheduled for the same day. John was kept on continuous cardiac monitoring and had a lumbar puncture performed to rule out intracranial infection, which returned normal.\n\n**Day 2\u20133: Early Management and Differential Warnings**\n\nThe EEG from day 2 showed frequent sharp\u2011wave discharges over the left temporoparietal region with evolving electrographic seizures, which suggested that the subdural hematoma was indeed the precipitating event. Based on the EEG findings and the known risk factor of a family history of epilepsy, Dr. Patel empirically started levetiracetam 500\u202fmg twice daily. The dose was chosen to balance efficacy and side effects because John\u2019s baseline liver function tests were normal, but his mother\u2019s alcoholism history made liver toxicity a concern for any future antiepileptic therapies.\n\nMeanwhile, the psychiatric team visited John, noting that the sudden stress of the accident had triggered a rebound of depressive symptoms: low mood, anhedonia, and intrusive thoughts of the fall. His sertraline dose remained unchanged for now. The migraine team was consulted, and John was given a trial of sumatriptan for acute headache, as the migraine phenotype was partially overlapping with his new post-traumatic headaches.\n\n**Day 4\u20135: Second Seizure and Med Change**\n\nDespite the levetiracetam, John had a second seizure at home on day\u202f4. It was a generalized tonic\u2013clonic event that lasted approximately 3 minutes. The family called emergency services, and John arrived at the ED with post\u2011ictal confusion. A repeat head CT showed a small increase in the size of the subdural collection, now 3\u202fmm with a midline shift of 4\u202fmm. Dr. Patel, after reviewing the imaging, decided to transfer John to the surgical floor for definitive management. However, an operative plan for a burr\u2011hole evacuation was put on hold, because the hematoma was considered to be small and the patient was otherwise clinically stable.\n\nThe neurology team, in consultation with the neurosurgeon, stepped up levetiracetam to 1000\u202fmg twice daily and added lacosamide 100\u202fmg once daily to broaden antiepileptic coverage. The family expressed anxiety, and Dr. Patel discussed the importance of adherence and the risk of breakthrough seizures. He also explained that the improvement of his depression and anxiety would help reduce the likelihood of seizure triggers.\n\n**Week 2: Rehabilitation and Stabilization**\n\nAfter the two seizures, John remained in the hospital for a week with serial imaging and EEG checks. A repeat CT after 48\u202fhours demonstrated slight regression of the hematoma to 2\u202fmm, and clinical symptoms had improved. His EEG now had only occasional sharp\u2011wave discharges, and there were no evolving seizures. The neurology team decided to maintain the dual antiepileptic drug regimen and monitor for side effects, such as dizziness or irritability, given John's history of depression and his own reports of feeling \u201cfoggy\u201d in the mornings.\n\nHe began a course of physical therapy under the guidance of Dr. Gomez, a certified neuro\u2011rehabilitator. John was able to ambulate with a short walker, though a mild right\u2011side spasticity persisted that was likely secondary to the left\u2011frontal lobe injury. The occupational therapist noted subtle deficits in executive function\u2014John struggled with task sequencing, which paralleled his migraine aura of \u201cbrain fog\u201d that sometimes made him feel unable to concentrate.\n\n**Week 3\u20134: Transition Home and Ongoing Improvement**\n\nOn discharge day, the treating team confirmed that John\u2019s headache pattern had shifted toward more of a chronic tension\u2011type rather than a migraine aura. His levetiracetam dose was scheduled to continue at 1000\u202fmg BID. Lacosamide remained at 100\u202fmg QHS. A final EEG 48\u202fhours before discharge showed no epileptiform discharges, providing reassurance of acute stability.\n\nJohn\u2019s follow\u2011up appointments were planned at the neurology clinic in one week, the psychiatric clinic two weeks after, and the neurosurgery outpatient clinic in six weeks for a follow\u2011up CT. He was advised to avoid alcohol and limit strenuous activity, to stay hydrated, and to continue taking sertraline 50\u202fmg daily to support mood stability. His mother\u2019s history of alcoholism was discussed with him in the context of avoiding family\u2011predisposed triggers\u2014most notably, limiting exposure to potentially triggering substances and ensuring a supportive, low\u2011stress home environment.\n\n**Outcome and Reflection**\n\nOver the next month, John reported that his headaches had become less frequent and no longer accompanied the classic migraine aura. His depressive symptoms had abated, and he reported an increase in mood and a renewed interest in his hobbies. The neurologist noted that John had had no further seizures and his EEG remained normal. Because John's brain injury was subacute but he had not progressed to a permanent epilepsy syndrome, he was considered \u201cimproving\u201d on the acuity scale. His risk for future seizures was lowered from a high suspicion (familial history and acute symptomatic event) to a moderate risk, contingent on continued AED compliance and careful monitoring. The rehabilitation teams noted improved gait speed and decreased spasticity, with an overall return to baseline functional mobility.\n\nJohn remained on a low\u2011dose levetiracetam regimen for a further six months, with plans to trial a weaning schedule if the EEG remained stable. He and his primary care provider also instituted an updated psychiatric care plan that included mindfulness\u2011based cognitive therapy to address the lingering cognitive fog and a relapse prevention strategy for depression. By the end of the third month, John had returned to his construction duties with a modified shift schedule, marking his return to life with the knowledge that his new neurological status, though improved, would require vigilance.",
  "timeline": [
    {
      "visit_number": 1,
      "visit_date": "2023-08-01",
      "clinician_specialty": "Emergency Medicine",
      "reason_for_visit": "Head injury with witnessed seizure post-accident",
      "is_related_to_main_illness": true,
      "note": "Chief Complaint: Head injury with witnessed seizure post\u2011accident.\n\nHistory of Present Illness: 35\u2011year\u2011old male with a history of migraine and depression presents to the ED after a fall from his own height. Witnesses observed a generalized tonic seizure lasting approximately 1 minute. He was subsequently found to be loss of consciousness immediately post\u2011fall. He reports a throbbing headache, blurred vision, and photophobia.\n\nPast Medical History: Migraine, Depression.\nPast Surgical History: None.\nMedications: None.\nAllergies: NKDA.\nSocial History: Non\u2011smoker, occasional alcohol.\nFamily History: Positive for epilepsy (maternal side).\n\nPhysical Examination:\n- Vitals: BP 140/90 mmHg, HR 110/min (tachycardic), RR 20/min, Temp 98.6\u00b0F, SpO2 98% on room air.\n- General: Awake, alert, oriented x3, no acute distress.\n- HEENT: Laceration over frontal region, left-sided scalp tenderness.\n- Neurologic: Cranial nerves II\u2013XII intact. Strength 4+/5 on the right upper extremity, 5/5 elsewhere. No focal sensory deficits noted.\n- Cardiovascular: Regular rhythm, no murmurs.\n- Respiratory: Clear to auscultation bilaterally.\n- Abdomen: Soft, non\u2011tender.\n- Extremities: No edema, pulses 2+ at all sites.\n\nAssessment:\n1. Traumatic subdural hematoma (2\u202fmm left frontal) with mild midline shift \u2013 stable, requiring close neurologic monitoring.\n2. Generalized tonic seizure secondary to acute head trauma; differential includes acute post\u2011traumatic seizure versus underlying seizure disorder.\n3. Post\u2011ictal state \u2013 patient remains confused but oriented.\n\nPlan:\n1. Admit to Neurosurgery Observation Unit with continuous cardiac telemetry and neurologic monitoring.\n2. Order urgent EEG on the day of admission to evaluate for epileptiform activity.\n3. Continue IV isotonic fluids (1\u202fL NS) to maintain euvolemia.\n4. Consider starting levetiracetam 500\u202fmg PO BID once the patient can tolerate oral intake if EEG shows interictal discharges or to prophylactically reduce seizure recurrence.\n5. Neurosurgical consult to review imaging and determine need for burr hole or craniotomy \u2013 currently observation due to small size and stable appearance.\n6. Repeat head CT in 12\u202fhrs if neurological status changes or if patient becomes obtunded.\n7. Pain management: Acetaminophen 650\u202fmg PO q6h PRN, avoid NSAIDs due to potential for bleeding.\n8. Continue screening for depression; arrange psychiatric follow\u2011up.\n9. Educate patient regarding signs of increased intracranial pressure (reduced consciousness, worsening headache, vomiting, new neurologic deficits) and advise urgent return to ED if any.\n\nDisposition: Admitted.\n\nSignificant Labs: CBC, BMP, lactate, lumbar puncture (normal).",
      "patient_age": 35,
      "patient_sex": "M",
      "symptoms": [
        "Loss of consciousness",
        "Generalized tonic seizure",
        "Headache",
        "Blurred vision",
        "Photophobia"
      ],
      "vitals": {
        "BP": "140/90",
        "HR": "110",
        "RR": "20",
        "Temp": "98.6\u00b0F",
        "SpO2": "98%"
      },
      "relevant_history": [
        "Traumatic brain injury",
        "History of migraines",
        "History of depression",
        "Family history of epilepsy"
      ],
      "known_conditions": [],
      "current_medications": [],
      "allergies": [],
      "visit_scenario": "John presents to the ED after a fall with a witnessed generalized tonic seizure. He is brought to the trauma bay, initial vital signs are stable but tachycardic. A noncontrast head CT is obtained, revealing a 2\u202fmm left frontal subdural hematoma with mild midline shift and no skull fracture. CBC, BMP, and lactate are within normal limits. A lumbar puncture is performed to rule out infection and is normal. An initial seizure is treated with IV lorazepam 1\u202fmg, which terminates the episode. He is admitted to the neurosurgical observation unit for monitoring with continuous cardiac telemetry and an EEG is scheduled for the same day. He is also placed on IV fluids 1\u202fL NS and observed for postictal recovery.",
      "examination_findings": [
        "Head laceration at frontal region",
        "Left\u2011sided scalp tenderness",
        "Neurologic exam: awake, oriented, CN II\u2013XII intact",
        "Right\u2011sided weakness 4+/5",
        "Left arm clonic during seizure"
      ],
      "tests_ordered": [
        "Head CT",
        "CBC",
        "BMP",
        "Lactate",
        "EEG planned",
        "Lumbar puncture"
      ],
      "test_results": [
        "Head CT: 2\u202fmm left frontal subdural hematoma with mild midline shift, no fracture",
        "CBC: WBC 9.5, Hgb 13.7, Plt 240",
        "BMP: normal",
        "Lactate 1.2",
        "Lumbar puncture: normal opening pressure, no infection"
      ],
      "treatments_administered": [
        "IV lorazepam 1\u202fmg",
        "IV fluids 1\u202fL NS",
        "Sedation as needed",
        "Admitted to neurosurgical unit"
      ],
      "patient_response": "Seizure terminated after lorazepam; remained alert with mild postictal confusion.",
      "disease_progression_notes": "Acute symptomatic seizure due to traumatic subdural hematoma. Monitoring required. EEG pending."
    },
    {
      "visit_number": 2,
      "visit_date": "2023-08-03",
      "clinician_specialty": "Neurology",
      "reason_for_visit": "Follow-up after traumatic injury; assessment of seizure activity",
      "is_related_to_main_illness": true,
      "note": "Subjective: 35\u2011year\u2011old male presents for post\u2011traumatic injury follow\u2011up. Denies new seizures; reports ongoing throbbing headache, photophobia, mild confusion. No nausea or vomiting. No new focal deficits beyond left arm weakness noted on exam.\n\nObjective: Vitals: BP 138/86, HR 102, RR 18, Temp 98.4\u00b0F, SpO2 98%. Neurologic exam reveals left upper motor neuron pattern: left arm 4+/5, mild spasticity, brisk reflexes. No focal seizure observed. All other systems normal. Repeat head CT shows slight increase to 3\u202fmm subdural hematoma without midline shift. Routine EEG demonstrates frequent sharp\u2011wave discharges over the left temporoparietal region. Liver function panel remains within normal limits.\n\nAssessment:\n1. Enlarging subdural hematoma (post\u2011traumatic subdural hematoma) \u2013 slight increase but asymptomatic.\n2. Post\u2011traumatic epilepsy \u2013 interictal sharp\u2011wave discharges; no clinical seizures to date.\n3. Migraine headache \u2013 episodic history, current headache throbbing, photophobia.\n4. Depressive episode \u2013 currently stable on sertraline.\n\nPlan:\n- Initiate levetiracetam 500\u202fmg PO BID for seizure prophylaxis.\n- Prescribe sumatriptan 50\u202fmg PRN for migraine headaches.\n- Continue sertraline 50\u202fmg daily.\n- Educate patient on medication adherence and red\u2011flag neurological signs (new weakness, worsening headache, visual changes).\n- Repeat head CT in 1 month or sooner if clinical status changes.\n- Seizure diary and headache log to be maintained.\n- Follow up in neurology clinic in 2 weeks; outpatient neurosurgery consult in 4 weeks.\n- Psychiatric follow\u2011up as needed; monitor mood symptoms.\n\nThis plan addresses both the acute neurosurgical concern and the risk of post\u2011traumatic epilepsy while optimizing headache control and mood stability.",
      "patient_age": 35,
      "patient_sex": "M",
      "symptoms": [
        "Headache (throbbing, migraine\u2011like)",
        "Photophobia",
        "Mild confusion",
        "No seizures since admission"
      ],
      "vitals": {
        "BP": "138/86",
        "HR": "102",
        "RR": "18",
        "Temp": "98.4\u00b0F",
        "SpO2": "98%"
      },
      "relevant_history": [
        "Previous focal seizure on admission",
        "History of migraines (episodic, usually treated with OTC analgesics)",
        "Depressive episodes treated with sertraline 50\u202fmg/day",
        "Family history of untreated epilepsy in father"
      ],
      "known_conditions": [
        "Migraine",
        "Depressive episode"
      ],
      "current_medications": [
        "Sertraline 50\u202fmg daily"
      ],
      "allergies": [],
      "visit_scenario": "Neuro exam reveals left upper motor neuron pattern: left arm weakness 4+/5, mild spasticity, brisk left reflexes. No focal seizure observed. A routine EEG is performed, showing frequent sharp\u2011wave discharges over the left temporoparietal region with evolving electrographic seizures. A repeat head CT shows a slight increase to 3\u202fmm subdural hematoma without midline shift. Liver function tests remain normal. Based on the EEG findings and known family history, levetiracetam 500\u202fmg PO BID is initiated. Sumatriptan 50\u202fmg is prescribed PRN for headache; sertraline is continued unchanged. The patient is instructed on medication adherence and signs of breakthrough seizures.",
      "examination_findings": [
        "Neuro exam: left arm 4+/5, mild spasticity, brisk reflexes",
        "Other systems normal"
      ],
      "tests_ordered": [
        "EEG",
        "Repeat head CT",
        "Liver function panel"
      ],
      "test_results": [
        "EEG: Frequent sharp\u2011wave discharges over left temporoparietal region with evolving electrographic seizures",
        "Head CT: slight increase to 3\u202fmm subdural hematoma, no midline shift",
        "LFTs normal"
      ],
      "treatments_administered": [
        "Levetiracetam 500\u202fmg PO BID",
        "Sumatriptan 50\u202fmg PRN for headache",
        "Continue sertraline 50\u202fmg daily"
      ],
      "patient_response": "Patient reports ongoing headaches but no seizures; tolerates new medication well.",
      "disease_progression_notes": "Early focal seizure activity secondary to subdural hematoma. Initiated antiepileptic therapy with levetiracetam. Headache may represent post\u2011traumatic migraine; considered triptan therapy."
    },
    {
      "visit_number": 3,
      "visit_date": "2023-08-05",
      "clinician_specialty": "Neurosurgery",
      "reason_for_visit": "Recurrent generalized tonic\u2011clonic seizure; evaluation for surgical intervention",
      "is_related_to_main_illness": true,
      "note": "**Chief Complaint**: Recurrent generalized tonic\u2011clonic seizure; evaluation for surgical intervention.\n\n**History of Present Illness**: 35\u2011year\u2011old male presents to the neurosurgery clinic on 2023-08-05 for a post\u2011ictal neurological assessment. The patient reports a generalized tonic\u2011clonic seizure that occurred at home approximately 3 minutes in duration, after which he experienced confusion and a brief period of disorientation that resolved spontaneously within 30 minutes. He denies any new focal seizures or loss of consciousness after the event. He describes a throbbing headache localized to the left frontal region, mild left arm weakness, and increased sensation of \u201ctightness\u201d in the left arm. He has not had any seizures in the past 24 hours.\n\n**Past Medical History**: Migraine, depression, epilepsy (provoked), left frontal subdural hematoma from fall 4 days ago.\n\n**Medications**: Sertraline 50 mg daily, Levetiracetam 500 mg BID (now increased to 1000 mg BID), Lacosamide 100 mg QHS (new), Lorazepam 2 mg PRN every 6 hours.\n\n**Allergies**: NKDA.\n\n**Review of Systems**: Positive for post\u2011ictal confusion, headache, left arm weakness. No dizziness, visual changes, dysarthria, or new focal deficits.\n\n**Physical Examination**:\n- **Vital Signs**: BP 135/85 mmHg, HR 100 bpm, RR 18/min, Temp 98.4\u00b0F, SpO\u2082 97%\n- **General**: Alert, oriented to person, place, time.\n- **Neurologic**: Cranial nerves II-XII grossly intact. Motor: Left upper extremity 4+/5 strength, mild spasticity; right upper extremity 5/5. Reflexes: Brisk left biceps; remaining reflexes 2+. Sensory intact. Coordination normal. Gait unremarkable.\n- **Other**: No focal deficits beyond left arm weakness.\n\n**Imaging & Studies**:\n- **Head CT**: 3 mm subdural hematoma anterior left frontal; 4 mm midline shift; no new bleed.\n- **MRI Brain**: Confirms subdural collection anterior left frontal, no parenchymal lesions.\n- **EEG**: Occasional sharp-wave discharges, no evolving seizures.\n- **Laboratory**: CBC, CMP within normal limits.\n\n**Assessment**:\n1. **Recurrent generalized tonic\u2011clonic epilepsy** secondary to trauma\u2011induced subdural hematoma \u2013 likely provoked by ongoing subdural collection.\n2. **Small left frontal subdural hematoma with mild midline shift** \u2013 no acute mass effect, clinically stable.\n3. **Left upper\u2011motor\u2011neuron pattern (weakness, spasticity, brisk reflexes)** \u2013 likely due to subdural irritation.\n4. **Possible post\u2011traumatic epilepsy** \u2013 given history of seizures within days of injury.\n\n**Plan**:\n- **Medical Management**: Continue Levetiracetam 1000 mg BID. Add Lacosamide 100 mg QHS to broaden anti\u2011epileptic coverage. Provision of Lorazepam 2 mg PRN every 6 hours for breakthrough seizures.\n- **Surgical Consideration**: Burr\u2011hole evacuation deferred due to small volume and clinical stability; will repeat neuroimaging in 2\u20134 weeks.\n- **Monitoring**: Maintain seizure diary, headache log, and document any focal changes.\n- **Mental Health**: Discussed potential mood improvements with seizure control; encourage adherence to Sertraline. Provide reassurance regarding anxiety.\n- **Follow\u2011Up**: Neurology follow\u2011up in 2 weeks; Neurosurgery outpatient visit in 4 weeks for repeat CT/MRI and possible surgical evaluation. Continue routine labs (CBC/CMP) annually; sooner if symptomatic.\n- **Patient Education**: Reviewed seizure warning signs, importance of medication adherence, and when to seek emergent care (e.g., prolonged seizures, new focal deficits).\n\n**Disposition**: Patient remains neurologically stable, no current seizures; discharged with updated medication regimen and follow\u2011up plan.",
      "patient_age": 35,
      "patient_sex": "M",
      "symptoms": [
        "Post\u2011ictal confusion after generalized tonic\u2011clonic seizure",
        "Headache",
        "Left arm weakness",
        "No current seizures"
      ],
      "vitals": {
        "BP": "135/85",
        "HR": "100",
        "RR": "18",
        "Temp": "98.4\u00b0F",
        "SpO2": "97%"
      },
      "relevant_history": [
        "Recent generalized tonic\u2011clonic seizure at home on day\u202f4",
        "Subdural hematoma on imaging",
        "Previous focal seizures during admission",
        "Depression managed with sertraline 50\u202fmg"
      ],
      "known_conditions": [
        "Migraine",
        "Depression",
        "Epilepsy (provoked)"
      ],
      "current_medications": [
        "Sertraline 50\u202fmg daily",
        "Levetiracetam 500\u202fmg BID"
      ],
      "allergies": [],
      "visit_scenario": "Patient presents with post\u2011ictal confusion following a generalized tonic\u2011clonic seizure that lasted approximately 3\u202fminutes. A repeat noncontrast head CT shows a 3\u202fmm subdural hematoma with a 4\u202fmm midline shift; no new bleed noted. The neurosurgeon discusses burr\u2011hole evacuation but opts against immediate surgery due to the small size of the hematoma and clinical stability. The neurology team increases levetiracetam to 1000\u202fmg BID and adds lacosamide 100\u202fmg QHS to broaden antiepileptic coverage. Lorazepam 2\u202fmg/6\u202fh PRN is made available for breakthrough seizures. The patient is counseled on medication adherence and seizure warning signs, and anxiety is addressed by explaining the potential benefit of seizure control on mood. No new seizures occur afterward.",
      "examination_findings": [
        "Neuro exam: left arm 4+/5 weakness, mild spasticity",
        "Right side normal",
        "Reflexes brisk left"
      ],
      "tests_ordered": [
        "Head CT",
        "MRI brain",
        "EEG",
        "CBC",
        "CMP"
      ],
      "test_results": [
        "Head CT: 3\u202fmm subdural hematoma, 4\u202fmm midline shift, no acute bleed",
        "EEG: Occasional sharp waves, no evolving seizures",
        "MRI: subdural collection anterior left frontal, no additional pathology",
        "CBC, CMP normal"
      ],
      "treatments_administered": [
        "Levetiracetam increased to 1000\u202fmg BID",
        "Lacosamide 100\u202fmg QHS added",
        "Lorazepam PRN 2\u202fmg/6\u202fh",
        "Continue sertraline 50\u202fmg daily"
      ],
      "patient_response": "Feels more stable; no seizures in past 24\u202fhrs; tolerates new meds with mild dizziness but no severe side effects.",
      "disease_progression_notes": "Subdural hematoma stable with slight enlargement; seizures persisting after monotherapy; dual AED chosen. Surgical intervention deferred due to risk/benefit."
    },
    {
      "visit_number": 4,
      "visit_date": "2023-08-12",
      "clinician_specialty": "Physical Medicine & Rehabilitation",
      "reason_for_visit": "Post\u2011acute rehab; evaluate functional recovery",
      "is_related_to_main_illness": true,
      "note": "Chief Complaint: Post\u2011acute rehabilitation; evaluation of functional recovery.\\n\\nHistory of Present Illness: 35\u2011year\u2011old male presents for follow\u2011up of traumatic subdural hematoma and post\u2011traumatic brain injury (TBI) status after recent fall with generalized tonic seizure. The patient has been on dual antiepileptic therapy (levetiracetam 1000\u202fmg BID, lacosamide 100\u202fmg QHS) and is taking sertraline for depression, sumatriptan for migraine, acetaminophen PRN, and lorazepam PRN. He reports mild right\u2011side spasticity, left arm weakness, executive dysfunction, and ongoing headaches. His mood has improved slightly and he notes increased functional independence. No new seizures reported.\\n\\nPhysical Exam: Vitals stable: BP 130/80, HR 90, RR 18, Temp 98.5\u202f\u00b0F, SpO\u2082 98%. Neurologic: Upper extremity strength left 4+/5, right 5/5; mild spasticity right side; gait stable with walker, no balance deficits noted. Cognitive: mild slowed processing, intact memory, executive function mildly impaired (task sequencing errors). Speech: pragmatic language normal.\\n\\nImaging/Tests: Repeat head CT shows regression of subdural hematoma to 2\u202fmm, no midline shift. CBC and CMP normal.\\n\\nAssessment: 1) Residual traumatic subdural hematoma (stable, regressed) \u2013 no surgical intervention indicated. 2) Mild right\u2011side spasticity \u2013 likely post\u2011TBI spasticity, responding to PT. 3) Left upper\u2011motor neuron pattern (moderate weakness) \u2013 consistent with frontal lobe injury; improving with therapy. 4) Executive dysfunction \u2013 early post\u2011TBI cognitive deficit; improved but warrants continued OT/ST intervention. 5) Post\u2011traumatic epilepsy risk \u2013 controlled with current AEDs; no new seizures. 6) Migraine headaches \u2013 improving, likely related to TBI.\\n\\nPlan: Continue current medication regimen unchanged. Maintain PT 3x/week focused on gait, strength, and spasticity management. OT continue task sequencing drills with emphasis on executive function. ST to continue pragmatic language and executive tasks. Continue dual AED therapy; monitor for breakthrough seizures. Maintain headache and seizure diary. Repeat head CT in 6 weeks to confirm continued regression. Neuro\u2011rehab goal: ambulate without assistive device within 3 months, improve executive task sequencing to <3 errors per task. Neuro\u2011psychiatric follow\u2011up with neurology in 2 weeks; neurosurgery outpatient review in 4 weeks. Patient educated on seizure precautions and signs of recurrence. Encourage adherence to medications and therapy sessions.\\n\\nPatient understanding confirmed. The patient will return for the next multidisciplinary rehabilitation evaluation on 2023-09\u201101 or sooner if new symptoms arise.",
      "patient_age": 35,
      "patient_sex": "M",
      "symptoms": [
        "Mild right\u2011side spasticity",
        "Left arm weakness",
        "Executive dysfunction",
        "Ongoing headaches"
      ],
      "vitals": {
        "BP": "130/80",
        "HR": "90",
        "RR": "18",
        "Temp": "98.5\u00b0F",
        "SpO2": "98%"
      },
      "relevant_history": [
        "Rehab initiation",
        "Previous seizures and ongoing AED therapy",
        "Depression",
        "Migraine history"
      ],
      "known_conditions": [
        "Migraine",
        "Depression",
        "Epilepsy (provoked)"
      ],
      "current_medications": [
        "Sertraline 50\u202fmg daily",
        "Levetiracetam 1000\u202fmg BID",
        "Lacosamide 100\u202fmg QHS"
      ],
      "allergies": [],
      "visit_scenario": "The neuro\u2011rehab team evaluates the patient\u2019s gait, muscle tone, and cognitive function. Upper extremity strength is left 4+/5, right 5/5; mild spasticity noted on the right side. Gait assessment with a walker is stable. Occupational therapy focuses on task sequencing and executive function; speech therapy evaluates pragmatic language. Repeat head CT demonstrates regression to a 2\u202fmm subdural hematoma with no midline shift. Baseline labs are normal. The patient is encouraged to continue dual AED therapy and is reassured about seizure risk reduction. Rehabilitation goals include ambulation without aid and improved executive tasks.",
      "examination_findings": [
        "Upper extremity strength: left 4+/5, right 5/5",
        "Mild spasticity on right side",
        "Gait: stable with walker",
        "Cognitive: mild slowed processing, intact memory"
      ],
      "tests_ordered": [
        "Repeat head CT",
        "Baseline CBC",
        "CMP"
      ],
      "test_results": [
        "Head CT: 2\u202fmm subdural hematoma, regression, no midline shift",
        "CBC & CMP normal"
      ],
      "treatments_administered": [
        "Physical therapy 3\u00d7/week: gait & strength",
        "Occupational therapy: task sequencing drills",
        "Speech therapy: executive function tasks",
        "Continue current medications"
      ],
      "patient_response": "Reports less headache, mood improved slightly, feels more functional.",
      "disease_progression_notes": "Gradual improvement in neurological deficits, hematoma regressing, low seizure frequency. Continue dual AED until stable."
    },
    {
      "visit_number": 5,
      "visit_date": "2023-08-19",
      "clinician_specialty": "Neurology",
      "reason_for_visit": "Discharge planning; review of investigations, medications, future follow\u2011up",
      "is_related_to_main_illness": true,
      "note": "Visit 5 \u2013 2023\u201108\u201119\n\nChief Complaint: Discharge planning; review of investigations, medications, future follow\u2011up\n\nHistory: 35\u2011year\u2011old male with migraine, major depressive disorder, traumatic subdural hematoma, traumatic brain injury, and post\u2011traumatic epilepsy. Current admission for left frontal subdural hematoma (2\u202fmm) with residual left\u2011arm weakness and mild spasticity. Chronic meds: levetiracetam 1000\u202fmg PO BID, lacosamide 100\u202fmg QHS, sertraline 50\u202fmg daily, sumatriptan 50\u202fmg PRN, lorazepam 2\u202fmg PRN as needed, acetaminophen 650\u202fmg q6h PRN. No known allergies.\n\nReview of Systems: Patient reports mild headaches, mild residual spasticity, mood stable. No reports of new seizures, focal neurologic deficits, or autonomic instability.\n\nPhysical Exam: Vitals stable: BP 128/78, HR 88, RR 18, Temp 98.6\u202f\u00b0F, SpO\u2082 98%. Neurologic exam: strength 4+/5 in left upper extremity, mild right\u2011sided spasticity, gait normal with walker use, no cranial nerve deficits, sensory intact. No focal seizures observed.\n\nInvestigations: Final pre\u2011discharge EEG \u2013 normal. Repeat head CT 48\u202fh prior to discharge \u2013 stable, no midline shift. CBC and CMP \u2013 within normal limits.\n\nAssessment: Stabilized post\u2011traumatic subdural hematoma with no evidence of ongoing hemorrhage; post\u2011traumatic epilepsy under therapeutic control; post\u2011traumatic headache evolving toward tension\u2011type; residual spasticity and left\u2011arm weakness consistent with previous injury but not progressing.\n\nPlan:\n1. Discharge medication regimen: \n   - Levetiracetam 1000\u202fmg PO BID\n   - Lacosamide 100\u202fmg QHS\n   - Sertraline 50\u202fmg daily\n   - Sumatriptan 50\u202fmg PO PRN for headache flare\n   - Lorazepam 2\u202fmg PO PRN every 6\u202fhrs if agitation/seizure\n   - Acetaminophen 650\u202fmg PO q6h PRN for pain\n2. Educate patient on medication adherence, seizure\u2011prevention strategies, and headache diary maintenance.\n3. Discharge instructions: Continue PT and OT as per rehab plan, maintain walker use, avoid high\u2011risk activities until fully cleared.\n4. Follow\u2011up schedule: \n   - 1\u202fweek: Neurology rehab assessment\n   - 2\u202fweeks: Psychiatry follow\u2011up for mood and medication titration\n   - 6\u202fweeks: Neurosurgery outpatient CT to confirm hematoma resolution\n5. Patient to report any new seizures, worsening headaches, or neurological deficits immediately.\n\nDisposition: Patient ready for discharge; consent obtained, all medications reviewed and explained.\n\nSigned: _________________________\nNeurology (MD)",
      "patient_age": 35,
      "patient_sex": "M",
      "symptoms": [
        "No seizures",
        "Mild headaches",
        "Mild residual spasticity",
        "Mood stable"
      ],
      "vitals": {
        "BP": "128/78",
        "HR": "88",
        "RR": "18",
        "Temp": "98.6\u00b0F",
        "SpO2": "98%"
      },
      "relevant_history": [
        "No breakthrough seizures",
        "Headache evolution from migraine to tension\u2011type",
        "Depression stable on sertraline"
      ],
      "known_conditions": [
        "Migraine",
        "Depression",
        "Epilepsy (provoked)"
      ],
      "current_medications": [
        "Sertraline 50\u202fmg daily",
        "Levetiracetam 1000\u202fmg BID",
        "Lacosamide 100\u202fmg QHS",
        "Sumatriptan 50\u202fmg PRN"
      ],
      "allergies": [],
      "visit_scenario": "Final pre\u2011discharge evaluation confirms no seizures on recent EEG, a stable 2\u202fmm subdural hematoma on CT, and normal labs. The patient is educated on seizure warning signs and medication adherence. Discharge medications are finalized: levetiracetam 1000\u202fmg BID, lacosamide 100\u202fmg QHS, sertraline 50\u202fmg daily, sumatriptan 50\u202fmg PRN for any headache flare. The neurology team sets future follow\u2011up visits in 1\u202fweek (rehab), 2\u202fweeks (psychiatry), and 6\u202fweeks (neurosurgery outpatient CT).",
      "examination_findings": [
        "Neuro exam normal except left arm 4+/5 weakness, mild right spasticity",
        "Gait normal with walker"
      ],
      "tests_ordered": [
        "Final EEG (pre\u2011discharge)",
        "Repeat head CT 48\u202fh prior to discharge",
        "CBC",
        "CMP"
      ],
      "test_results": [
        "EEG: Normal, no epileptiform discharges",
        "CT: 2\u202fmm subdural hematoma, no shift",
        "CBC & CMP normal"
      ],
      "treatments_administered": [
        "Finalize discharge meds",
        "Counsel on seizure warning signs",
        "Reinforce medication adherence"
      ],
      "patient_response": "No further seizures; headaches less frequent; mood improved significantly.",
      "disease_progression_notes": "Patient has no evidence of acute seizures; hematoma resolved; risk of future seizures moderate; plan for follow\u2011up."
    },
    {
      "visit_number": 6,
      "visit_date": "2023-08-26",
      "clinician_specialty": "Neurology",
      "reason_for_visit": "Routine post\u2011discharge follow\u2011up",
      "is_related_to_main_illness": true,
      "note": "Chief Complaint: Routine post\u2011discharge follow\u2011up.\n\nHistory of Present Illness: 35\u2011year\u2011old male presents for routine neurology follow\u2011up 3\u202fdays after discharge. Reports no seizures, no new headaches, and mood remains stable. Patient continues to track a seizure and headache diary. No new medications or side effects reported. No new symptoms since discharge.\n\nPast Medical History: Migraine, major depressive disorder, traumatic subdural hematoma, traumatic brain injury, post\u2011traumatic epilepsy, provoked epilepsy.\n\nMedications: Sertraline 50\u202fmg PO daily, Levetiracetam 1000\u202fmg PO BID, Lacosamide 100\u202fmg QHS, Sumatriptan 50\u202fmg PRN, Lorazepam 2\u202fmg PRN every 6\u202fh, Acetaminophen 650\u202fmg PO q6h PRN. No known allergies.\n\nReview of Systems: Positive for stable mood; negative for neurologic events, headache, or medication side effects.\n\nPhysical Examination:\n- Vital Signs: BP 125/78\u202fmmHg, HR 86\u202fbpm, RR 18\u202f/min, Temp 98.4\u202f\u00b0F, SpO\u2082 98\u202f%.\n- General: Alert, oriented. \n- Neurologic: Cranial nerves II\u2011XII intact. Strength: left upper extremity 4+/5, right upper extremity 5/5, lower extremities 5/5. No spasticity. Gait steady, heel\u2011to\u2011toe. No sensory deficits. Reflexes 2+ symmetrical. No cerebellar dysfunction.\n- Headache: None. \n\nLaboratory Results: CBC, CMP, and LFTs all within normal limits. No evidence of AED toxicity.\n\nAssessment: Stable post\u2011traumatic epilepsy on dual AED therapy with no breakthrough seizures. Residual mild left arm weakness likely from chronic post\u2011traumatic changes; no new deficits. Migraine well\u2011controlled on PRN sumatriptan. Depression remains stable. Traumatic subdural hematoma has resolved to 2\u202fmm with no midline shift. Neuro exam remains unchanged.\n\nPlan:\n1. Continue current medication regimen as ordered.\n2. Discuss AED taper: If outpatient EEG remains normal and there are no clinical events, consider gradual taper of levetiracetam and lacosamide over 6\u202fmonths.\n3. Order an outpatient EEG to confirm continued seizure suppression.\n4. Provide brief counseling on medication adherence and seizure\u2011precaution education.\n5. Schedule next neurology visit in 6\u202fweeks to reassess neurologic status, review EEG, and plan tapering if appropriate.\n6. Continue PT/OT as per rehab team.\n7. Encourage patient to maintain seizure & headache diary.\n\nDisposition: Stable discharge home from clinic. Patient advised to call clinic if seizures, new neurologic symptoms, or medication intolerances occur.\n\nThank you. Signatures:_________",
      "patient_age": 35,
      "patient_sex": "M",
      "symptoms": [
        "Routine review; no seizures or headaches",
        "Mood stable"
      ],
      "vitals": {
        "BP": "125/78",
        "HR": "86",
        "RR": "18",
        "Temp": "98.4\u00b0F",
        "SpO2": "98%"
      },
      "relevant_history": [
        "Stable on dual AED, no breakthrough seizures",
        "No severe side effects reported"
      ],
      "known_conditions": [
        "Migraine",
        "Depression",
        "Epilepsy (provoked)"
      ],
      "current_medications": [
        "Sertraline 50\u202fmg daily",
        "Levetiracetam 1000\u202fmg BID",
        "Lacosamide 100\u202fmg QHS",
        "Sumatriptan 50\u202fmg PRN"
      ],
      "allergies": [],
      "visit_scenario": "The neurology clinic review confirms stable neuro exam: left arm strength 4+/5, no spasticity, no seizure activity. CBC, CMP, and LFTs are normal, with no evidence of AED toxicity. The patient is encouraged to continue current medications and is informed of the possibility to taper AEDs after 6\u202fmonths if EEG remains normal. Next appointment scheduled for 6\u202fweeks to monitor progress and discuss gradual tapering. A brief counseling session on medication adherence is also offered.",
      "examination_findings": [
        "Neuro exam normal; mild left arm weakness 4+/5",
        "Gait steady; no spasticity noted"
      ],
      "tests_ordered": [
        "CBC",
        "CMP",
        "LFTs",
        "EEG (optional)"
      ],
      "test_results": [
        "CBC, CMP, LFTs normal"
      ],
      "treatments_administered": [
        "Continue current meds",
        "Discuss potential AED taper after 6\u202fmonths"
      ],
      "patient_response": "Headaches rare, mood stable, no side effects.",
      "disease_progression_notes": "Stable on dual AED; no seizures; consider gradual taper after 6 months based on EEG & clinical stability."
    },
    {
      "visit_number": 7,
      "visit_date": "2023-09-02",
      "clinician_specialty": "Psychiatry",
      "reason_for_visit": "Depression management, evaluate mood, medication review",
      "is_related_to_main_illness": true,
      "note": "Chief Complaint: 35\u2011year\u2011old male presents for routine follow\u2011up of depression management and medication review.\n\nHistory of Present Illness: The patient reports feeling \"a bit better\" with occasional low mood, no suicidal ideation or homicidal thoughts. He has not had any new seizures or significant headaches. He continues to manage migraine with sumatriptan PRN. He feels hopeful, less anxious, and is eager to resume work.\n\nPast Psychiatric History: Prior depressive episodes treated with sertraline. Current minimal depressive symptomatology (PHQ\u20119 score 6) and minimal anxiety (GAD\u20117 score 5) observed.\n\nPast Neurologic History: Post\u2011traumatic subdural hematoma and provoked epilepsy managed with levetiracetam and lacosamide. Recent neuroimaging stable.\n\nMedications: Sertraline 50\u202fmg PO daily, levetiracetam 1\u202f000\u202fmg PO BID, lacosamide 100\u202fmg PO QHS, sumatriptan 50\u202fmg PO PRN.\n\nAllergies: NKDA.\n\nPhysical Examination:\n- Vitals: BP 127/80, HR 84, RR 18, Temp 98.5\u202f\u00b0F, SpO\u2082 98%.\n- Mental Status: Alert, oriented x3, mood mildly upbeat, affect congruent, no SI/HI observed.\n\nAssessment:\n1. Minimal depressive symptoms (current PHQ\u20119 6) \u2013 stable, likely well\u2011controlled on sertraline.\n2. Minimal generalized anxiety \u2013 stable.\n3. Controlled provoked epilepsy \u2013 no new seizures, medications tolerated.\n4. Migraine \u2013 managed PRN.\n\nPlan:\n- Continue sertraline 50\u202fmg PO daily.\n- Reinforce adherence to current AED regimen.\n- Encourage mindfulness\u2011based CBT and a low\u2011stress environment to reduce seizure triggers.\n- Continue seizure and headache diary.\n- No medication changes at this visit.\n- Schedule psychiatric follow\u2011up in 2 weeks.\n- Routine neurology follow\u2011up per prior plan; repeat head CT in 6 weeks; EEG as indicated.\n- Encourage regular physical therapy and occupational therapy per neurorehabilitation.\n- Counsel patient on lifestyle modifications (sleep hygiene, stress management) and when to seek emergency care (new seizures, worsening headaches, suicidal ideation).\n\nDisposition: Patient discharged home with instructions to maintain current regimen and diary; instructions to call office if any new seizures or psychiatric concerns arise.\n\nProvider: [Signature].",
      "patient_age": 35,
      "patient_sex": "M",
      "symptoms": [
        "Mood slightly improved, occasional low mood",
        "No suicidal ideation"
      ],
      "vitals": {
        "BP": "127/80",
        "HR": "84",
        "RR": "18",
        "Temp": "98.5\u00b0F",
        "SpO2": "98%"
      },
      "relevant_history": [
        "Previous depressive episodes, sertraline therapy",
        "Seizure history (provoked)"
      ],
      "known_conditions": [
        "Migraine",
        "Depression",
        "Epilepsy (provoked)"
      ],
      "current_medications": [
        "Sertraline 50\u202fmg daily",
        "Levetiracetam 1000\u202fmg BID",
        "Lacosamide 100\u202fmg QHS",
        "Sumatriptan 50\u202fmg PRN"
      ],
      "allergies": [],
      "visit_scenario": "PHQ\u20119 assessed mood, yielding a score of 6 (minimal depression). GAD\u20117 indicated minimal anxiety. The psychiatrist reinforced the benefit of consistent medication adherence, explored mindfulness\u2011based CBT, and discussed the importance of a low\u2011stress environment to reduce seizure triggers. No medication change was made; sertraline 50\u202fmg continued. The patient expressed optimism about returning to work and adherence to the treatment plan.",
      "examination_findings": [
        "Mental status: alert, oriented, mood mildly upbeat, affect congruent, no suicidal ideation"
      ],
      "tests_ordered": [
        "PHQ\u20119 questionnaire",
        "GAD\u20117"
      ],
      "test_results": [
        "PHQ\u20119 score 6 (minimal depression)",
        "GAD\u20117 score 5 (minimal anxiety)"
      ],
      "treatments_administered": [
        "Reinforce mindfulness CBT",
        "Continue sertraline 50\u202fmg daily"
      ],
      "patient_response": "Feels hopeful, less anxious, wants to resume work.",
      "disease_progression_notes": "Depression controlled on sertraline; minimal side effects; mood improvement supports seizure risk reduction."
    }
  ],
  "notes": [
    {
      "visit_number": 1,
      "clinician_specialty": "Emergency Medicine",
      "note_date": "2023-08-01",
      "content": "Chief Complaint: Head injury with witnessed seizure post\u2011accident.\n\nHistory of Present Illness: 35\u2011year\u2011old male with a history of migraine and depression presents to the ED after a fall from his own height. Witnesses observed a generalized tonic seizure lasting approximately 1 minute. He was subsequently found to be loss of consciousness immediately post\u2011fall. He reports a throbbing headache, blurred vision, and photophobia.\n\nPast Medical History: Migraine, Depression.\nPast Surgical History: None.\nMedications: None.\nAllergies: NKDA.\nSocial History: Non\u2011smoker, occasional alcohol.\nFamily History: Positive for epilepsy (maternal side).\n\nPhysical Examination:\n- Vitals: BP 140/90 mmHg, HR 110/min (tachycardic), RR 20/min, Temp 98.6\u00b0F, SpO2 98% on room air.\n- General: Awake, alert, oriented x3, no acute distress.\n- HEENT: Laceration over frontal region, left-sided scalp tenderness.\n- Neurologic: Cranial nerves II\u2013XII intact. Strength 4+/5 on the right upper extremity, 5/5 elsewhere. No focal sensory deficits noted.\n- Cardiovascular: Regular rhythm, no murmurs.\n- Respiratory: Clear to auscultation bilaterally.\n- Abdomen: Soft, non\u2011tender.\n- Extremities: No edema, pulses 2+ at all sites.\n\nAssessment:\n1. Traumatic subdural hematoma (2\u202fmm left frontal) with mild midline shift \u2013 stable, requiring close neurologic monitoring.\n2. Generalized tonic seizure secondary to acute head trauma; differential includes acute post\u2011traumatic seizure versus underlying seizure disorder.\n3. Post\u2011ictal state \u2013 patient remains confused but oriented.\n\nPlan:\n1. Admit to Neurosurgery Observation Unit with continuous cardiac telemetry and neurologic monitoring.\n2. Order urgent EEG on the day of admission to evaluate for epileptiform activity.\n3. Continue IV isotonic fluids (1\u202fL NS) to maintain euvolemia.\n4. Consider starting levetiracetam 500\u202fmg PO BID once the patient can tolerate oral intake if EEG shows interictal discharges or to prophylactically reduce seizure recurrence.\n5. Neurosurgical consult to review imaging and determine need for burr hole or craniotomy \u2013 currently observation due to small size and stable appearance.\n6. Repeat head CT in 12\u202fhrs if neurological status changes or if patient becomes obtunded.\n7. Pain management: Acetaminophen 650\u202fmg PO q6h PRN, avoid NSAIDs due to potential for bleeding.\n8. Continue screening for depression; arrange psychiatric follow\u2011up.\n9. Educate patient regarding signs of increased intracranial pressure (reduced consciousness, worsening headache, vomiting, new neurologic deficits) and advise urgent return to ED if any.\n\nDisposition: Admitted.\n\nSignificant Labs: CBC, BMP, lactate, lumbar puncture (normal).",
      "symptoms_reported": [
        "Loss of consciousness",
        "Generalized tonic seizure",
        "Headache",
        "Blurred vision",
        "Photophobia"
      ],
      "vitals": {
        "BP": "140/90 mmHg",
        "HR": "110/min",
        "RR": "20/min",
        "Temp": "98.6\u00b0F",
        "SpO2": "98%"
      },
      "tests_ordered": [
        "Head CT",
        "CBC",
        "BMP",
        "Lactate",
        "EEG",
        "Lumbar puncture"
      ],
      "diagnoses_considered": [
        "Head injury with acute subdural hematoma",
        "Traumatic brain injury with seizure",
        "Post\u2011traumatic epilepsy",
        "Migraine exacerbation"
      ],
      "medications": [
        "IV lorazepam 1\u202fmg (1 dose)",
        "IV 1\u202fL NS"
      ],
      "follow_up_recommendations": [
        "Neurosurgery observation with telemetry",
        "Urgent EEG",
        "Consider levetiracetam if EEG indicates ongoing risk",
        "Repeat head CT if neurological status changes",
        "Pain control with acetaminophen",
        "Psychiatric follow\u2011up for depression",
        "Patient education on warning signs of worsening intracranial pressure"
      ]
    },
    {
      "visit_number": 2,
      "clinician_specialty": "Neurology",
      "note_date": "2023-08-03",
      "content": "Subjective: 35\u2011year\u2011old male presents for post\u2011traumatic injury follow\u2011up. Denies new seizures; reports ongoing throbbing headache, photophobia, mild confusion. No nausea or vomiting. No new focal deficits beyond left arm weakness noted on exam.\n\nObjective: Vitals: BP 138/86, HR 102, RR 18, Temp 98.4\u00b0F, SpO2 98%. Neurologic exam reveals left upper motor neuron pattern: left arm 4+/5, mild spasticity, brisk reflexes. No focal seizure observed. All other systems normal. Repeat head CT shows slight increase to 3\u202fmm subdural hematoma without midline shift. Routine EEG demonstrates frequent sharp\u2011wave discharges over the left temporoparietal region. Liver function panel remains within normal limits.\n\nAssessment:\n1. Enlarging subdural hematoma (post\u2011traumatic subdural hematoma) \u2013 slight increase but asymptomatic.\n2. Post\u2011traumatic epilepsy \u2013 interictal sharp\u2011wave discharges; no clinical seizures to date.\n3. Migraine headache \u2013 episodic history, current headache throbbing, photophobia.\n4. Depressive episode \u2013 currently stable on sertraline.\n\nPlan:\n- Initiate levetiracetam 500\u202fmg PO BID for seizure prophylaxis.\n- Prescribe sumatriptan 50\u202fmg PRN for migraine headaches.\n- Continue sertraline 50\u202fmg daily.\n- Educate patient on medication adherence and red\u2011flag neurological signs (new weakness, worsening headache, visual changes).\n- Repeat head CT in 1 month or sooner if clinical status changes.\n- Seizure diary and headache log to be maintained.\n- Follow up in neurology clinic in 2 weeks; outpatient neurosurgery consult in 4 weeks.\n- Psychiatric follow\u2011up as needed; monitor mood symptoms.\n\nThis plan addresses both the acute neurosurgical concern and the risk of post\u2011traumatic epilepsy while optimizing headache control and mood stability.",
      "symptoms_reported": [
        "Throbbing headache",
        "Photophobia",
        "Mild confusion",
        "No seizures since admission"
      ],
      "vitals": {
        "BP": "138/86",
        "HR": "102",
        "RR": "18",
        "Temp": "98.4\u00b0F",
        "SpO2": "98%"
      },
      "tests_ordered": [
        "EEG",
        "Repeat head CT",
        "Liver function panel"
      ],
      "diagnoses_considered": [
        "Post\u2011traumatic epilepsy",
        "Enlarging subdural hematoma",
        "Migraine headache",
        "Depressive episode",
        "Medication\u2011induced headache"
      ],
      "medications": [
        "Levetiracetam 500 mg PO BID",
        "Sumatriptan 50 mg PRN",
        "Sertraline 50 mg daily"
      ],
      "follow_up_recommendations": [
        "Neuro follow\u2011up in 2 weeks",
        "Repeat head CT in 1 month or sooner if neurological changes",
        "Maintain seizure and headache diary",
        "Report any new neurological symptoms or seizures immediately",
        "Schedule neurosurgery outpatient visit in 4 weeks",
        "Continue psychiatric follow\u2011up as needed"
      ]
    },
    {
      "visit_number": 3,
      "clinician_specialty": "Neurosurgery",
      "note_date": "2023-08-05",
      "content": "**Chief Complaint**: Recurrent generalized tonic\u2011clonic seizure; evaluation for surgical intervention.\n\n**History of Present Illness**: 35\u2011year\u2011old male presents to the neurosurgery clinic on 2023-08-05 for a post\u2011ictal neurological assessment. The patient reports a generalized tonic\u2011clonic seizure that occurred at home approximately 3 minutes in duration, after which he experienced confusion and a brief period of disorientation that resolved spontaneously within 30 minutes. He denies any new focal seizures or loss of consciousness after the event. He describes a throbbing headache localized to the left frontal region, mild left arm weakness, and increased sensation of \u201ctightness\u201d in the left arm. He has not had any seizures in the past 24 hours.\n\n**Past Medical History**: Migraine, depression, epilepsy (provoked), left frontal subdural hematoma from fall 4 days ago.\n\n**Medications**: Sertraline 50 mg daily, Levetiracetam 500 mg BID (now increased to 1000 mg BID), Lacosamide 100 mg QHS (new), Lorazepam 2 mg PRN every 6 hours.\n\n**Allergies**: NKDA.\n\n**Review of Systems**: Positive for post\u2011ictal confusion, headache, left arm weakness. No dizziness, visual changes, dysarthria, or new focal deficits.\n\n**Physical Examination**:\n- **Vital Signs**: BP 135/85 mmHg, HR 100 bpm, RR 18/min, Temp 98.4\u00b0F, SpO\u2082 97%\n- **General**: Alert, oriented to person, place, time.\n- **Neurologic**: Cranial nerves II-XII grossly intact. Motor: Left upper extremity 4+/5 strength, mild spasticity; right upper extremity 5/5. Reflexes: Brisk left biceps; remaining reflexes 2+. Sensory intact. Coordination normal. Gait unremarkable.\n- **Other**: No focal deficits beyond left arm weakness.\n\n**Imaging & Studies**:\n- **Head CT**: 3 mm subdural hematoma anterior left frontal; 4 mm midline shift; no new bleed.\n- **MRI Brain**: Confirms subdural collection anterior left frontal, no parenchymal lesions.\n- **EEG**: Occasional sharp-wave discharges, no evolving seizures.\n- **Laboratory**: CBC, CMP within normal limits.\n\n**Assessment**:\n1. **Recurrent generalized tonic\u2011clonic epilepsy** secondary to trauma\u2011induced subdural hematoma \u2013 likely provoked by ongoing subdural collection.\n2. **Small left frontal subdural hematoma with mild midline shift** \u2013 no acute mass effect, clinically stable.\n3. **Left upper\u2011motor\u2011neuron pattern (weakness, spasticity, brisk reflexes)** \u2013 likely due to subdural irritation.\n4. **Possible post\u2011traumatic epilepsy** \u2013 given history of seizures within days of injury.\n\n**Plan**:\n- **Medical Management**: Continue Levetiracetam 1000 mg BID. Add Lacosamide 100 mg QHS to broaden anti\u2011epileptic coverage. Provision of Lorazepam 2 mg PRN every 6 hours for breakthrough seizures.\n- **Surgical Consideration**: Burr\u2011hole evacuation deferred due to small volume and clinical stability; will repeat neuroimaging in 2\u20134 weeks.\n- **Monitoring**: Maintain seizure diary, headache log, and document any focal changes.\n- **Mental Health**: Discussed potential mood improvements with seizure control; encourage adherence to Sertraline. Provide reassurance regarding anxiety.\n- **Follow\u2011Up**: Neurology follow\u2011up in 2 weeks; Neurosurgery outpatient visit in 4 weeks for repeat CT/MRI and possible surgical evaluation. Continue routine labs (CBC/CMP) annually; sooner if symptomatic.\n- **Patient Education**: Reviewed seizure warning signs, importance of medication adherence, and when to seek emergent care (e.g., prolonged seizures, new focal deficits).\n\n**Disposition**: Patient remains neurologically stable, no current seizures; discharged with updated medication regimen and follow\u2011up plan.",
      "symptoms_reported": [
        "post-ictal confusion",
        "headache",
        "left arm weakness",
        "no current seizures"
      ],
      "vitals": {
        "BP": "135/85",
        "HR": "100",
        "RR": "18",
        "Temp": "98.4\u00b0F",
        "SpO2": "97%"
      },
      "tests_ordered": [
        "Head CT",
        "MRI brain",
        "EEG",
        "CBC",
        "CMP"
      ],
      "diagnoses_considered": [
        "Traumatic subdural hematoma secondary to seizure activity",
        "Recurrent generalized tonic\u2011clonic epilepsy secondary to trauma",
        "Post\u2011traumatic epilepsy",
        "Medication\u2011resistant epilepsy",
        "Left frontal cortical irritation"
      ],
      "medications": [
        "Levetiracetam 1000 mg BID",
        "Lacosamide 100 mg QHS",
        "Lorazepam 2 mg PRN every 6 hrs",
        "Sertraline 50 mg daily"
      ],
      "follow_up_recommendations": [
        "Neurology follow\u2011up in 2 weeks",
        "Neurosurgery outpatient visit in 4 weeks for repeat imaging and possible surgical evaluation",
        "Maintain seizure and headache diary",
        "Monitor for new focal deficits or headache exacerbation",
        "Review CBC/CMP annually or sooner if symptomatic"
      ]
    },
    {
      "visit_number": 4,
      "clinician_specialty": "Physical Medicine & Rehabilitation",
      "note_date": "2023-08-12",
      "content": "Chief Complaint: Post\u2011acute rehabilitation; evaluation of functional recovery.\\n\\nHistory of Present Illness: 35\u2011year\u2011old male presents for follow\u2011up of traumatic subdural hematoma and post\u2011traumatic brain injury (TBI) status after recent fall with generalized tonic seizure. The patient has been on dual antiepileptic therapy (levetiracetam 1000\u202fmg BID, lacosamide 100\u202fmg QHS) and is taking sertraline for depression, sumatriptan for migraine, acetaminophen PRN, and lorazepam PRN. He reports mild right\u2011side spasticity, left arm weakness, executive dysfunction, and ongoing headaches. His mood has improved slightly and he notes increased functional independence. No new seizures reported.\\n\\nPhysical Exam: Vitals stable: BP 130/80, HR 90, RR 18, Temp 98.5\u202f\u00b0F, SpO\u2082 98%. Neurologic: Upper extremity strength left 4+/5, right 5/5; mild spasticity right side; gait stable with walker, no balance deficits noted. Cognitive: mild slowed processing, intact memory, executive function mildly impaired (task sequencing errors). Speech: pragmatic language normal.\\n\\nImaging/Tests: Repeat head CT shows regression of subdural hematoma to 2\u202fmm, no midline shift. CBC and CMP normal.\\n\\nAssessment: 1) Residual traumatic subdural hematoma (stable, regressed) \u2013 no surgical intervention indicated. 2) Mild right\u2011side spasticity \u2013 likely post\u2011TBI spasticity, responding to PT. 3) Left upper\u2011motor neuron pattern (moderate weakness) \u2013 consistent with frontal lobe injury; improving with therapy. 4) Executive dysfunction \u2013 early post\u2011TBI cognitive deficit; improved but warrants continued OT/ST intervention. 5) Post\u2011traumatic epilepsy risk \u2013 controlled with current AEDs; no new seizures. 6) Migraine headaches \u2013 improving, likely related to TBI.\\n\\nPlan: Continue current medication regimen unchanged. Maintain PT 3x/week focused on gait, strength, and spasticity management. OT continue task sequencing drills with emphasis on executive function. ST to continue pragmatic language and executive tasks. Continue dual AED therapy; monitor for breakthrough seizures. Maintain headache and seizure diary. Repeat head CT in 6 weeks to confirm continued regression. Neuro\u2011rehab goal: ambulate without assistive device within 3 months, improve executive task sequencing to <3 errors per task. Neuro\u2011psychiatric follow\u2011up with neurology in 2 weeks; neurosurgery outpatient review in 4 weeks. Patient educated on seizure precautions and signs of recurrence. Encourage adherence to medications and therapy sessions.\\n\\nPatient understanding confirmed. The patient will return for the next multidisciplinary rehabilitation evaluation on 2023-09\u201101 or sooner if new symptoms arise.",
      "symptoms_reported": [
        "mild right\u2011side spasticity",
        "left arm weakness",
        "executive dysfunction",
        "ongoing headaches"
      ],
      "vitals": {
        "BP": "130/80",
        "HR": "90",
        "RR": "18",
        "Temp": "98.5\u00b0F",
        "SpO2": "98%"
      },
      "tests_ordered": [
        "Repeat head CT",
        "Baseline CBC",
        "CMP"
      ],
      "diagnoses_considered": [
        "Residual post\u2011traumatic subdural hematoma",
        "Post\u2011traumatic spasticity",
        "Left upper motor neuron weakness",
        "Executive dysfunction post\u2011TBI",
        "Post\u2011traumatic epilepsy risk",
        "Migraine headache"
      ],
      "medications": [
        "Sertraline 50 mg daily",
        "Levetiracetam 1000 mg PO BID",
        "Lacosamide 100 mg QHS",
        "Lorazepam 2 mg PRN every 6 hrs",
        "Sumatriptan 50 mg PRN",
        "Acetaminophen 650 mg PO q6h PRN"
      ],
      "follow_up_recommendations": [
        "Continue PT 3\u00d7/week, OT task sequencing, ST executive tasks",
        "Monitor headache diary and seizure diary",
        "Maintain current AED therapy",
        "Repeat head CT in 6 weeks",
        "Neurology follow\u2011up in 2 weeks",
        "Neurosurgery outpatient in 4 weeks",
        "Review functional goals at next visit (2023\u201109\u201101)"
      ]
    },
    {
      "visit_number": 5,
      "clinician_specialty": "Neurology",
      "note_date": "2023-08-19",
      "content": "Visit 5 \u2013 2023\u201108\u201119\n\nChief Complaint: Discharge planning; review of investigations, medications, future follow\u2011up\n\nHistory: 35\u2011year\u2011old male with migraine, major depressive disorder, traumatic subdural hematoma, traumatic brain injury, and post\u2011traumatic epilepsy. Current admission for left frontal subdural hematoma (2\u202fmm) with residual left\u2011arm weakness and mild spasticity. Chronic meds: levetiracetam 1000\u202fmg PO BID, lacosamide 100\u202fmg QHS, sertraline 50\u202fmg daily, sumatriptan 50\u202fmg PRN, lorazepam 2\u202fmg PRN as needed, acetaminophen 650\u202fmg q6h PRN. No known allergies.\n\nReview of Systems: Patient reports mild headaches, mild residual spasticity, mood stable. No reports of new seizures, focal neurologic deficits, or autonomic instability.\n\nPhysical Exam: Vitals stable: BP 128/78, HR 88, RR 18, Temp 98.6\u202f\u00b0F, SpO\u2082 98%. Neurologic exam: strength 4+/5 in left upper extremity, mild right\u2011sided spasticity, gait normal with walker use, no cranial nerve deficits, sensory intact. No focal seizures observed.\n\nInvestigations: Final pre\u2011discharge EEG \u2013 normal. Repeat head CT 48\u202fh prior to discharge \u2013 stable, no midline shift. CBC and CMP \u2013 within normal limits.\n\nAssessment: Stabilized post\u2011traumatic subdural hematoma with no evidence of ongoing hemorrhage; post\u2011traumatic epilepsy under therapeutic control; post\u2011traumatic headache evolving toward tension\u2011type; residual spasticity and left\u2011arm weakness consistent with previous injury but not progressing.\n\nPlan:\n1. Discharge medication regimen: \n   - Levetiracetam 1000\u202fmg PO BID\n   - Lacosamide 100\u202fmg QHS\n   - Sertraline 50\u202fmg daily\n   - Sumatriptan 50\u202fmg PO PRN for headache flare\n   - Lorazepam 2\u202fmg PO PRN every 6\u202fhrs if agitation/seizure\n   - Acetaminophen 650\u202fmg PO q6h PRN for pain\n2. Educate patient on medication adherence, seizure\u2011prevention strategies, and headache diary maintenance.\n3. Discharge instructions: Continue PT and OT as per rehab plan, maintain walker use, avoid high\u2011risk activities until fully cleared.\n4. Follow\u2011up schedule: \n   - 1\u202fweek: Neurology rehab assessment\n   - 2\u202fweeks: Psychiatry follow\u2011up for mood and medication titration\n   - 6\u202fweeks: Neurosurgery outpatient CT to confirm hematoma resolution\n5. Patient to report any new seizures, worsening headaches, or neurological deficits immediately.\n\nDisposition: Patient ready for discharge; consent obtained, all medications reviewed and explained.\n\nSigned: _________________________\nNeurology (MD)",
      "symptoms_reported": [
        "Mild headaches",
        "Mild residual spasticity",
        "Mood stable"
      ],
      "vitals": {
        "BP": "128/78",
        "HR": "88",
        "RR": "18",
        "Temp": "98.6\u00b0F",
        "SpO2": "98%"
      },
      "tests_ordered": [
        "Final EEG (pre\u2011discharge)",
        "Repeat head CT 48\u202fh prior to discharge",
        "CBC",
        "CMP"
      ],
      "diagnoses_considered": [
        "Post\u2011traumatic epilepsy",
        "Post\u2011traumatic headache/migraine",
        "Residual spasticity from TBI",
        "Left upper motor neuron deficit"
      ],
      "medications": [
        "Levetiracetam 1000 mg PO BID",
        "Lacosamide 100 mg QHS",
        "Sertraline 50 mg daily",
        "Sumatriptan 50 mg PRN",
        "Lorazepam 2 mg PRN",
        "Acetaminophen 650 mg PO q6h PRN"
      ],
      "follow_up_recommendations": [
        "1\u2011week neurology rehab visit",
        "2\u2011week psychiatry follow\u2011up",
        "6\u2011week neurosurgery outpatient CT scan",
        "Continue PT/OT per rehab plan",
        "Maintain medication adherence and headache diary"
      ]
    },
    {
      "visit_number": 6,
      "clinician_specialty": "Neurology",
      "note_date": "2023-08-26",
      "content": "Chief Complaint: Routine post\u2011discharge follow\u2011up.\n\nHistory of Present Illness: 35\u2011year\u2011old male presents for routine neurology follow\u2011up 3\u202fdays after discharge. Reports no seizures, no new headaches, and mood remains stable. Patient continues to track a seizure and headache diary. No new medications or side effects reported. No new symptoms since discharge.\n\nPast Medical History: Migraine, major depressive disorder, traumatic subdural hematoma, traumatic brain injury, post\u2011traumatic epilepsy, provoked epilepsy.\n\nMedications: Sertraline 50\u202fmg PO daily, Levetiracetam 1000\u202fmg PO BID, Lacosamide 100\u202fmg QHS, Sumatriptan 50\u202fmg PRN, Lorazepam 2\u202fmg PRN every 6\u202fh, Acetaminophen 650\u202fmg PO q6h PRN. No known allergies.\n\nReview of Systems: Positive for stable mood; negative for neurologic events, headache, or medication side effects.\n\nPhysical Examination:\n- Vital Signs: BP 125/78\u202fmmHg, HR 86\u202fbpm, RR 18\u202f/min, Temp 98.4\u202f\u00b0F, SpO\u2082 98\u202f%.\n- General: Alert, oriented. \n- Neurologic: Cranial nerves II\u2011XII intact. Strength: left upper extremity 4+/5, right upper extremity 5/5, lower extremities 5/5. No spasticity. Gait steady, heel\u2011to\u2011toe. No sensory deficits. Reflexes 2+ symmetrical. No cerebellar dysfunction.\n- Headache: None. \n\nLaboratory Results: CBC, CMP, and LFTs all within normal limits. No evidence of AED toxicity.\n\nAssessment: Stable post\u2011traumatic epilepsy on dual AED therapy with no breakthrough seizures. Residual mild left arm weakness likely from chronic post\u2011traumatic changes; no new deficits. Migraine well\u2011controlled on PRN sumatriptan. Depression remains stable. Traumatic subdural hematoma has resolved to 2\u202fmm with no midline shift. Neuro exam remains unchanged.\n\nPlan:\n1. Continue current medication regimen as ordered.\n2. Discuss AED taper: If outpatient EEG remains normal and there are no clinical events, consider gradual taper of levetiracetam and lacosamide over 6\u202fmonths.\n3. Order an outpatient EEG to confirm continued seizure suppression.\n4. Provide brief counseling on medication adherence and seizure\u2011precaution education.\n5. Schedule next neurology visit in 6\u202fweeks to reassess neurologic status, review EEG, and plan tapering if appropriate.\n6. Continue PT/OT as per rehab team.\n7. Encourage patient to maintain seizure & headache diary.\n\nDisposition: Stable discharge home from clinic. Patient advised to call clinic if seizures, new neurologic symptoms, or medication intolerances occur.\n\nThank you. Signatures:_________",
      "symptoms_reported": [
        "No seizures",
        "No headaches",
        "Mood stable"
      ],
      "vitals": {
        "BP": "125/78",
        "HR": "86",
        "RR": "18",
        "Temp": "98.4\u00b0F",
        "SpO2": "98%"
      },
      "tests_ordered": [
        "EEG"
      ],
      "diagnoses_considered": [
        "Post\u2011traumatic epilepsy",
        "Migraine",
        "Residual neurological deficit from traumatic brain injury",
        "Depressive disorder"
      ],
      "medications": [
        "Sertraline 50 mg PO daily",
        "Levetiracetam 1000 mg PO BID",
        "Lacosamide 100 mg PO QHS",
        "Sumatriptan 50 mg PRN",
        "Lorazepam 2 mg PRN",
        "Acetaminophen 650 mg PO q6h PRN"
      ],
      "follow_up_recommendations": [
        "Outpatient EEG",
        "6\u2011week neurology follow\u2011up",
        "Continue PT/OT",
        "Maintain seizure & headache diary",
        "Contact clinic for new neurologic events or medication issues"
      ]
    },
    {
      "visit_number": 7,
      "clinician_specialty": "Psychiatry",
      "note_date": "2023-09-02",
      "content": "Chief Complaint: 35\u2011year\u2011old male presents for routine follow\u2011up of depression management and medication review.\n\nHistory of Present Illness: The patient reports feeling \"a bit better\" with occasional low mood, no suicidal ideation or homicidal thoughts. He has not had any new seizures or significant headaches. He continues to manage migraine with sumatriptan PRN. He feels hopeful, less anxious, and is eager to resume work.\n\nPast Psychiatric History: Prior depressive episodes treated with sertraline. Current minimal depressive symptomatology (PHQ\u20119 score 6) and minimal anxiety (GAD\u20117 score 5) observed.\n\nPast Neurologic History: Post\u2011traumatic subdural hematoma and provoked epilepsy managed with levetiracetam and lacosamide. Recent neuroimaging stable.\n\nMedications: Sertraline 50\u202fmg PO daily, levetiracetam 1\u202f000\u202fmg PO BID, lacosamide 100\u202fmg PO QHS, sumatriptan 50\u202fmg PO PRN.\n\nAllergies: NKDA.\n\nPhysical Examination:\n- Vitals: BP 127/80, HR 84, RR 18, Temp 98.5\u202f\u00b0F, SpO\u2082 98%.\n- Mental Status: Alert, oriented x3, mood mildly upbeat, affect congruent, no SI/HI observed.\n\nAssessment:\n1. Minimal depressive symptoms (current PHQ\u20119 6) \u2013 stable, likely well\u2011controlled on sertraline.\n2. Minimal generalized anxiety \u2013 stable.\n3. Controlled provoked epilepsy \u2013 no new seizures, medications tolerated.\n4. Migraine \u2013 managed PRN.\n\nPlan:\n- Continue sertraline 50\u202fmg PO daily.\n- Reinforce adherence to current AED regimen.\n- Encourage mindfulness\u2011based CBT and a low\u2011stress environment to reduce seizure triggers.\n- Continue seizure and headache diary.\n- No medication changes at this visit.\n- Schedule psychiatric follow\u2011up in 2 weeks.\n- Routine neurology follow\u2011up per prior plan; repeat head CT in 6 weeks; EEG as indicated.\n- Encourage regular physical therapy and occupational therapy per neurorehabilitation.\n- Counsel patient on lifestyle modifications (sleep hygiene, stress management) and when to seek emergency care (new seizures, worsening headaches, suicidal ideation).\n\nDisposition: Patient discharged home with instructions to maintain current regimen and diary; instructions to call office if any new seizures or psychiatric concerns arise.\n\nProvider: [Signature].",
      "symptoms_reported": [
        "Mood slightly improved, occasional low mood",
        "No suicidal ideation"
      ],
      "vitals": {
        "BP": "127/80",
        "HR": "84",
        "RR": "18",
        "Temp": "98.5\u00b0F",
        "SpO2": "98%"
      },
      "tests_ordered": [
        "PHQ-9 questionnaire",
        "GAD-7"
      ],
      "diagnoses_considered": [
        "Minimal depression",
        "Minimal generalized anxiety",
        "Controlled provoked epilepsy",
        "Migraine",
        "Subdural hematoma (stable)"
      ],
      "medications": [
        "Sertraline 50 mg PO daily",
        "Levetiracetam 1000 mg PO BID",
        "Lacosamide 100 mg PO QHS",
        "Sumatriptan 50 mg PO PRN"
      ],
      "follow_up_recommendations": [
        "Psychiatry follow\u2011up in 2 weeks",
        "Neuro\u2011rehab PT/OT continued per schedule",
        "Maintain seizure and headache diary",
        "Repeat head CT in 6 weeks",
        "Continue current medication regimen",
        "Encourage mindfulness\u2011based CBT and low\u2011stress environment",
        "Seek immediate care for new seizures or worsening headache"
      ]
    }
  ],
  "final_medical_history": {
    "demographics": {
      "age": 35,
      "sex": "M",
      "height": null,
      "weight": null
    },
    "known_conditions": [
      "Migraine",
      "Depression",
      "Traumatic subdural hematoma",
      "Traumatic brain injury",
      "Post-traumatic epilepsy",
      "Provoked epilepsy"
    ],
    "current_medications": [
      "Levetiracetam 1000 mg PO BID",
      "Lacosamide 100 mg QHS",
      "Lorazepam 2 mg PRN every 6 hrs",
      "Sertraline 50 mg daily",
      "Sumatriptan 50 mg PRN",
      "Acetaminophen 650 mg PO q6h PRN"
    ],
    "prior_visit_summaries": [
      "2023-08-01: 35\u2011year\u2011old male presents after fall with generalized tonic seizure and head injury. Exam shows left frontal subdural hematoma 2\u202fmm, mild midline shift. Admitted to neurosurgery observation with telemetry. Received IV lorazepam 1\u202fmg and 1\u202fL normal saline. Plan: perform EEG, repeat head CT if neuro status changes, start levetiracetam 500\u202fmg PO BID if indicated, administer acetaminophen 650\u202fmg q6h PRN, monitor neuro status, psychiatric follow\u2011up. No new allergies.",
      "2023-08-03: Follow\u2011up for post\u2011traumatic injury. Patient reports ongoing throbbing headache, photophobia, mild confusion; no new seizures. Neurologic exam shows left upper motor neuron pattern with left arm weakness 4+/5, mild spasticity. Repeat head CT shows slight increase to 3\u202fmm subdural hematoma, no midline shift. EEG demonstrates frequent sharp\u2011wave discharges over left temporoparietal region. Initiated levetiracetam 500\u202fmg BID for seizure prophylaxis, sumatriptan 50\u202fmg PRN for migraine, continued sertraline 50\u202fmg daily. Advised seizure and headache diary, scheduled neurology follow\u2011up in 2\u202fweeks, neurosurgery outpatient in 4\u202fweeks.",
      "2023-08-05: 35\u2011year\u2011old male with recurrent generalized tonic\u2011clonic seizure, post\u2011ictal confusion, left frontal headache, and left arm weakness. Examination: BP 135/85, HR 100, neuro exam shows left upper extremity 4+/5 strength, mild spasticity; otherwise intact. Imaging: head CT 3\u202fmm left frontal subdural hematoma with 4\u202fmm midline shift; MRI confirms subdural collection, no parenchymal lesions. EEG: occasional sharp\u2011wave discharges. Labs: CBC/CMP normal. Management: continue levetiracetam 1000\u202fmg PO BID, add lacosamide 100\u202fmg QHS, provide lorazepam 2\u202fmg PRN every 6\u202fhrs. Plan: repeat neuroimaging in 2\u20134\u202fweeks; neurology follow\u2011up in 2\u202fweeks; neurosurgery outpatient in 4\u202fweeks. Seizure and headache diary maintained.",
      "2023-08-12: Post\u2011acute rehab evaluation: mild right\u2011side spasticity, left arm weakness (4+/5 left, 5/5 right), executive dysfunction, ongoing headaches. Repeat head CT shows regression of subdural hematoma to 2\u202fmm, no midline shift. Vitals stable (BP 130/80, HR 90, RR 18, Temp 98.5\u00b0F, SpO\u2082 98%). Neuro\u2011rehab plan unchanged: continue PT 3x/week, OT task sequencing, ST executive tasks; maintain dual AED therapy, seizure and headache diary. Repeat head CT in 6 weeks; neurology follow\u2011up in 2 weeks; neurosurgery outpatient in 4 weeks.",
      "2023-08-19: Discharge planning for 35\u2011year\u2011old male with post\u2011traumatic subdural hematoma (2\u202fmm) and controlled post\u2011traumatic epilepsy. Physical exam stable; strength 4+/5 left upper extremity, mild right\u2011sided spasticity, no new seizures. Final EEG normal; repeat head CT stable. Discharged on levetiracetam 1000\u202fmg PO BID, lacosamide 100\u202fmg QHS, sertraline 50\u202fmg daily, sumatriptan 50\u202fmg PRN, lorazepam 2\u202fmg PRN, acetaminophen 650\u202fmg PO q6h PRN. Advised PT/OT continuation, walker use, seizure\u2011prevention education, headache diary. Follow\u2011ups: neurology rehab 1 week, psychiatry 2 weeks, neurosurgery CT 6 weeks.",
      "2023-08-26: Routine neurology follow\u2011up 3 days post\u2011discharge; patient reports no seizures, no new headaches, mood stable. Neurologic exam intact, mild left arm weakness 4+/5. Labs normal. EEG ordered. Plan: continue current med regimen; consider gradual AED taper over 6 months if EEG normal; continue PT/OT and diary maintenance.",
      "2023-09-02: 35\u2011year\u2011old male presents for routine depression follow\u2011up. Reports mild improvement in mood, no new seizures or headaches. Continues current medications (sertraline, levetiracetam, lacosamide, sumatriptan) with no changes. Advised to maintain seizure/ headache diary, continue PT/OT, repeat head CT in 6 weeks, next psychiatry visit in 2 weeks."
    ],
    "allergies": []
  }
}